.pre-commit-config.yaml
CHANGELOG.rst
MANIFEST.in
README.md
VERSION
setup.cfg
setup.py
freddy/__init__.py
freddy/exceptions.py
freddy/freddy.py
freddy/types.py
freddy.egg-info/PKG-INFO
freddy.egg-info/SOURCES.txt
freddy.egg-info/dependency_links.txt
freddy.egg-info/requires.txt
freddy.egg-info/top_level.txt
freddy.egg-info/zip-safe