Metadata-Version: 2.1
Name: freddy
Version: 3.1.0
Summary: Provides random samples of given json schema
Home-page: https://github.com/lferran/freddy
Author: Ferran Llamas
Author-email: llamas.arroniz@gmail.com
License: GNU General Public License V3
Platform: UNKNOWN
Classifier: Programming Language :: Python :: 3.8
Classifier: Intended Audience :: Developers
Classifier: Topic :: Software Development :: Libraries :: Python Modules
Provides-Extra: test
